.gitignore
service_wrapper-0.0.3.dist-info/METADATA
service_wrapper-0.0.3.dist-info/WHEEL
service_wrapper-0.0.3.dist-info/entry_points.txt
service_wrapper/__init__.py
service_wrapper/utils/__init__.py
service_wrapper/utils/service_tools.py
service_wrapper/utils/utils.py
service_wrapper/windows/__init__.py
service_wrapper/windows/base_service.py
service_wrapper/windows/ext.py
service_wrapper/windows/service_tools.py
service_wrapper/windows/service_utils.py
service_wrapper/windows/windows_wrapper.py
service_wrapper/wrapper.py
service_wrapper-0.0.3.dist-info/RECORD
