Metadata-Version: 2.1
Name: service_wrapper
Version: 0.0.3
Summary: Making services easy
Keywords: services,windows
Author-Email: Ofek Engel <ofek.engel@gmail.com>
License: MIT
Classifier: Development Status :: 2 - Pre-Alpha
Classifier: Intended Audience :: Developers
Classifier: Topic :: Software Development
Classifier: Topic :: System
Classifier: Topic :: System :: Operating System
Classifier: Programming Language :: Python
Classifier: Programming Language :: Python :: 3
Classifier: Operating System :: Microsoft
Classifier: Operating System :: Microsoft :: Windows
Classifier: Operating System :: POSIX :: Linux
Project-URL: Homepage, https://github.com/ofekengel/pyservice-wrapper
Requires-Python: >=3.12
Requires-Dist: pywin32>=308
Requires-Dist: typing-extensions>=4.12.2
